labmaze/__init__.py
labmaze/base.py
labmaze/defaults.py
labmaze/fixed_maze.py
labmaze/fixed_maze_test.py
labmaze/random_maze.py
labmaze/random_maze_test.py
labmaze/text_grid.py
labmaze/text_grid_test.py
labmaze/assets/__init__.py
labmaze/assets/assets_test.py
labmaze/assets/sky_01/bk.png
labmaze/assets/sky_01/dn.png
labmaze/assets/sky_01/ft.png
labmaze/assets/sky_01/lf.png
labmaze/assets/sky_01/rt.png
labmaze/assets/sky_01/up.png
labmaze/assets/sky_02/bk.png
labmaze/assets/sky_02/dn.png
labmaze/assets/sky_02/ft.png
labmaze/assets/sky_02/lf.png
labmaze/assets/sky_02/rt.png
labmaze/assets/sky_02/up.png
labmaze/assets/sky_03/bk.png
labmaze/assets/sky_03/dn.png
labmaze/assets/sky_03/ft.png
labmaze/assets/sky_03/lf.png
labmaze/assets/sky_03/rt.png
labmaze/assets/sky_03/up.png
labmaze/assets/style_01/4tile_d.png
labmaze/assets/style_01/ceiling_d.png
labmaze/assets/style_01/floor_blue_bright_d.png
labmaze/assets/style_01/floor_blue_d.png
labmaze/assets/style_01/floor_blue_team_d.png
labmaze/assets/style_01/floor_light_m.png
labmaze/assets/style_01/floor_orange_bright_d.png
labmaze/assets/style_01/floor_orange_d.png
labmaze/assets/style_01/floor_red_team_d.png
labmaze/assets/style_01/wall_blue_d.png
labmaze/assets/style_01/wall_cerise_d.png
labmaze/assets/style_01/wall_green_bright_d.png
labmaze/assets/style_01/wall_green_d.png
labmaze/assets/style_01/wall_light_m.png
labmaze/assets/style_01/wall_purple_d.png
labmaze/assets/style_01/wall_red_bright_d.png
labmaze/assets/style_01/wall_red_d.png
labmaze/assets/style_01/wall_yellow_d.png
labmaze/assets/style_02/floor_blue_bright_d.png
labmaze/assets/style_02/floor_blue_d.png
labmaze/assets/style_02/floor_green_bright_d.png
labmaze/assets/style_02/floor_green_d.png
labmaze/assets/style_02/floor_light_m.png
labmaze/assets/style_02/floor_orange_d.png
labmaze/assets/style_02/wall_blue_bright_d.png
labmaze/assets/style_02/wall_blue_d.png
labmaze/assets/style_02/wall_dblue_d.png
labmaze/assets/style_02/wall_lgreen_d.png
labmaze-1.0.6.dist-info/AUTHORS
labmaze-1.0.6.dist-info/LICENSE
labmaze-1.0.6.dist-info/METADATA
labmaze-1.0.6.dist-info/WHEEL
labmaze-1.0.6.dist-info/top_level.txt
labmaze-1.0.6.dist-info/RECORD
